jailbreak_evaluation/__init__.py
jailbreak_evaluation/multifaceted.py
jailbreak_evaluation/utils.py
jailbreak_evaluation-1.0.0.dist-info/METADATA
jailbreak_evaluation-1.0.0.dist-info/WHEEL
jailbreak_evaluation-1.0.0.dist-info/licenses/LICENSE
jailbreak_evaluation-1.0.0.dist-info/RECORD
