Metadata-Version: 2.3
Name: jailbreak-evaluation
Version: 1.0.0
Summary: A Python Library for Language Model Jailbreak Evaluation
Project-URL: Homepage, https://github.com/controllability/jailbreak-evaluation
Project-URL: Issues, https://github.com/controllability/jailbreak-evaluation/issues
Author: Controllability
License-File: LICENSE
Classifier: License :: OSI Approved :: Apache Software License
Classifier: Operating System :: OS Independent
Classifier: Programming Language :: Python :: 3
Requires-Python: >=3.8
Requires-Dist: nltk>=3.8.1
Requires-Dist: openai>=1.14.2
Requires-Dist: tenacity>=8.2.3
